brocode/__init__.py
brocode/banner.py
brocode/chat.py
brocode/cli.py
brocode/code_analysis.py
brocode/flow.py
brocode/register.py
brocode/actions/__init__.py
brocode/actions/chat.py
brocode/actions/user_input.py
brocode/actions/code_management/__init__.py
brocode/actions/code_management/code_agent.py
brocode/actions/code_management/code_generator/__init__.py
brocode/actions/code_management/code_generator/generate.py
brocode/actions/code_management/code_modifier/__init__.py
brocode/actions/code_management/code_modifier/modify.py
brocode/actions/code_management/utils/__init__.py
brocode/actions/code_management/utils/diff_viewer.py
brocode/actions/code_management/utils/error_handler.py
brocode/actions/code_management/utils/file_operations.py
brocode/actions/code_management/utils/file_selector.py
brocode/actions/code_management/utils/llm_handler.py
brocode/actions/code_management/utils/ui_helper.py
brocode/prompt_hub/chat.md
brocode/prompt_hub/code_generator.md
brocode/prompt_hub/code_modifier.md
brocode-0.1.3.dist-info/licenses/LICENSE
brocode-0.1.3.dist-info/METADATA
brocode-0.1.3.dist-info/WHEEL
brocode-0.1.3.dist-info/entry_points.txt
brocode-0.1.3.dist-info/top_level.txt
brocode-0.1.3.dist-info/RECORD
