Metadata-Version: 2.4
Name: brocode
Version: 0.1.3
Summary: brocode is a lightweight coding assistant in CLI
Requires-Python: >=3.12
License-File: LICENSE
Requires-Dist: broflow>=0.1.4
Requires-Dist: brollm>=0.1.2
Requires-Dist: broprompt>=0.1.5
Requires-Dist: click>=8.2.1
Requires-Dist: inquirerpy>=0.3.4
Requires-Dist: paperclip>=2.7.4
Requires-Dist: prompt-toolkit>=3.0.52
Requires-Dist: pydantic>=2.11.7
Requires-Dist: pyfiglet>=1.0.4
Requires-Dist: rich>=14.1.0
Dynamic: license-file
